sonotoria/__init__.py
sonotoria/jaml.py
sonotoria/jinja.py
sonotoria/template_config.py
sonotoria/extractor/__init__.py
sonotoria/extractor/cast.py
sonotoria/extractor/cond_extractor.py
sonotoria/extractor/extractor.py
sonotoria/extractor/for_loop.py
sonotoria/extractor/var_extractor.py
tests/__init__.py
tests/test_extract_conditionals.py
tests/test_extract_dict.py
tests/test_extract_list.py
tests/test_extract_variable.py
tests/test_init.py
tests/test_template.py
tests/test_yaml_loader.py
sonotoria-0.3.8.dist-info/LICENSE.txt
sonotoria-0.3.8.dist-info/METADATA
sonotoria-0.3.8.dist-info/WHEEL
sonotoria-0.3.8.dist-info/top_level.txt
sonotoria-0.3.8.dist-info/RECORD
